img2array/__init__.py
img2array/__main__.py
img2array/img2array.py
img2array-1.0.5.dist-info/METADATA
img2array-1.0.5.dist-info/WHEEL
img2array-1.0.5.dist-info/entry_points.txt
img2array-1.0.5.dist-info/licenses/LICENSE
img2array-1.0.5.dist-info/RECORD
