Metadata-Version: 2.1
Name: img2array
Version: 1.0.5
Summary: Prints the pixels of an image into an array of RGB values, that can be easily exported to embedded applications.
Project-URL: Homepage, https://codeberg.org/akselmo/img2array
Project-URL: Bug Tracker, https://codeberg.org/akselmo/img2array/issues
Author-email: Akseli Lahtinen <akselmo@akselmo.dev>
License-File: LICENSE
Classifier: License :: OSI Approved :: MIT License
Classifier: Operating System :: OS Independent
Classifier: Programming Language :: Python :: 3
Requires-Python: >=3.7
Requires-Dist: pillow==9.4.0
